ISPy/__init__.py
ISPy/data/__init__.py
ISPy/examples/__init__.py
ISPy/examples/hello_cpp/__init__.py
ISPy/examples/hello_f90/__init__.py
ISPy/examples/hello_py/__init__.py
ISPy/examples/hello_py/hello.py
ISPy/examples/vacuumtoair/__init__.py
ISPy/img/__init__.py
ISPy/img/align.py
ISPy/img/denoising.py
ISPy/img/interpolate2d.py
ISPy/inv/__init__.py
ISPy/inv/disambiguation.py
ISPy/io/__init__.py
ISPy/io/lapalma.py
ISPy/io/pyio.py
ISPy/io/solarnet.py
ISPy/rt/__init__.py
ISPy/sim/__init__.py
ISPy/spec/__init__.py
ISPy/spec/atlas.py
ISPy/spec/bfield.py
ISPy/spec/calib.py
ISPy/spec/chromis.py
ISPy/spec/crisp.py
ISPy/spec/crosstalk.py
ISPy/spec/wfa.py
ISPy/util/__init__.py
ISPy/util/azimuth.py
ISPy/util/cubeshow.py
ISPy/util/find.py
ISPy/util/gentools.py
ISPy/util/lineplot.py
ISPy/util/neural_estimation.py
ISPy/util/obs.py
ISPy/util/plottools.py
ISPy/util/rebin.py
ISPy/util/remap.py
ISPy/vis/__init__.py
ISPy/vis/readout_fn.py
ISPy/vis/show_hazel.py
ISPy_solar-0.2.1.dist-info/DESCRIPTION.rst
ISPy_solar-0.2.1.dist-info/METADATA
ISPy_solar-0.2.1.dist-info/RECORD
ISPy_solar-0.2.1.dist-info/WHEEL
ISPy_solar-0.2.1.dist-info/metadata.json
ISPy_solar-0.2.1.dist-info/top_level.txt
