Metadata-Version: 2.0
Name: ISPy-solar
Version: 0.2.1
Summary: ISPy is a Python library of commonly used tools at the Institute for Solar Physics (Stockholm University)
Home-page: https://github.com/ISP-SST/ISPy
Author: Diaz Baso, C. ; Vissers, G. ; Calvo, F. ; Pietrow, A. G. M. ; Yadav, R. ; de la Cruz Rodríguez, J. ; Zivadinovic, L.
Author-email: carlos.diaz@astro.su.se
License: UNKNOWN
Platform: UNKNOWN
Classifier: Programming Language :: Python :: 3.5
Classifier: License :: OSI Approved :: MIT License
Classifier: Operating System :: OS Independent
